sconce/__init__.py
sconce/model_analyzer.py
sconce/perf.py
sconce/pruner.py
sconce/quanter.py
sconce/sconce.py
sconce-1.0.2.dist-info/LICENSE.txt
sconce-1.0.2.dist-info/METADATA
sconce-1.0.2.dist-info/WHEEL
sconce-1.0.2.dist-info/top_level.txt
sconce-1.0.2.dist-info/RECORD
