Metadata-Version: 2.1
Name: sconce
Version: 1.0.2
Summary: Model Compresion Made Easy
Home-page: https://github.com/satabios/sconce
Author: Sathyaprakash Narayanan
Author-email: snaray17@ucsc.edu
License: MIT License
Keywords: sconce
Platform: UNKNOWN
Classifier: Intended Audience :: Developers
Classifier: Intended Audience :: Education
Classifier: Intended Audience :: Science/Research
Classifier: License :: OSI Approved :: MIT License
Classifier: Natural Language :: English
Classifier: Topic :: Scientific/Engineering
Classifier: Topic :: Scientific/Engineering :: Mathematics
Classifier: Topic :: Scientific/Engineering :: Artificial Intelligence
Classifier: Programming Language :: Python :: 3.9
Classifier: Programming Language :: Python :: 3.10
Classifier: Operating System :: OS Independent
Requires-Python: >=3.7
License-File: LICENSE.txt
Requires-Dist: alabaster==0.7.13
Requires-Dist: anyio==4.0.0
Requires-Dist: prettytable
Requires-Dist: argon2-cffi==23.1.0
Requires-Dist: argon2-cffi-bindings==21.2.0
Requires-Dist: arrow==1.3.0
Requires-Dist: asttokens==2.4.1
Requires-Dist: async-lru==2.0.4
Requires-Dist: attrs==23.1.0
Requires-Dist: Babel==2.13.1
Requires-Dist: beautifulsoup4==4.12.2
Requires-Dist: black==23.11.0
Requires-Dist: bleach==6.1.0
Requires-Dist: certifi==2023.7.22
Requires-Dist: cffi==1.16.0
Requires-Dist: charset-normalizer==3.3.2
Requires-Dist: click==8.1.7
Requires-Dist: cmake==3.27.7
Requires-Dist: comm==0.2.0
Requires-Dist: contourpy==1.2.0
Requires-Dist: cycler==0.12.1
Requires-Dist: debugpy==1.8.0
Requires-Dist: decorator==5.1.1
Requires-Dist: defusedxml==0.7.1
Requires-Dist: docutils==0.18.1
Requires-Dist: exceptiongroup==1.1.3
Requires-Dist: executing==2.0.1
Requires-Dist: fast-pytorch-kmeans==0.2.0.1
Requires-Dist: fastjsonschema==2.19.0
Requires-Dist: filelock==3.13.1
Requires-Dist: flake8==6.1.0
Requires-Dist: fonttools==4.44.0
Requires-Dist: fqdn==1.5.1
Requires-Dist: fsspec==2023.10.0
Requires-Dist: h5py==3.10.0
Requires-Dist: huggingface-hub==0.17.3
Requires-Dist: idna==3.4
Requires-Dist: imagesize==1.4.1
Requires-Dist: iniconfig==2.0.0
Requires-Dist: ipdb==0.13.13
Requires-Dist: ipykernel==6.26.0
Requires-Dist: ipython==8.17.2
Requires-Dist: ipywidgets==8.1.1
Requires-Dist: isoduration==20.11.0
Requires-Dist: jedi==0.19.1
Requires-Dist: Jinja2==3.1.2
Requires-Dist: json5==0.9.14
Requires-Dist: jsonpointer==2.4
Requires-Dist: jsonschema==4.20.0
Requires-Dist: jsonschema-specifications==2023.11.1
Requires-Dist: jupyter==1.0.0
Requires-Dist: jupyter-console==6.6.3
Requires-Dist: jupyter-events==0.9.0
Requires-Dist: jupyter-lsp==2.2.0
Requires-Dist: jupyter-client==8.6.0
Requires-Dist: jupyter-core==5.5.0
Requires-Dist: jupyter-server==2.10.1
Requires-Dist: jupyter-server-terminals==0.4.4
Requires-Dist: jupyterlab==4.0.9
Requires-Dist: jupyterlab-pygments==0.2.2
Requires-Dist: jupyterlab-widgets==3.0.9
Requires-Dist: jupyterlab-server==2.25.2
Requires-Dist: kiwisolver==1.4.5
Requires-Dist: lit==17.0.4
Requires-Dist: MarkupSafe==2.1.3
Requires-Dist: matplotlib==3.8.1
Requires-Dist: matplotlib-inline==0.1.6
Requires-Dist: mccabe==0.7.0
Requires-Dist: mistune==3.0.2
Requires-Dist: mpmath==1.3.0
Requires-Dist: mypy-extensions==1.0.0
Requires-Dist: nbclient==0.9.0
Requires-Dist: nbconvert==7.11.0
Requires-Dist: nbformat==5.9.2
Requires-Dist: nest-asyncio==1.5.8
Requires-Dist: networkx==3.2.1
Requires-Dist: nir==0.2.0
Requires-Dist: nirtorch==0.2.1
Requires-Dist: notebook==7.0.6
Requires-Dist: notebook-shim==0.2.3
Requires-Dist: numpy==1.26.1
Requires-Dist: nvidia-cublas-cu12==12.1.3.1
Requires-Dist: nvidia-cuda-cupti-cu12==12.1.105
Requires-Dist: nvidia-cuda-nvrtc-cu12==12.1.105
Requires-Dist: nvidia-cuda-runtime-cu12==12.1.105
Requires-Dist: nvidia-cudnn-cu12==8.9.2.26
Requires-Dist: nvidia-cufft-cu12==11.0.2.54
Requires-Dist: nvidia-curand-cu12==10.3.2.106
Requires-Dist: nvidia-cusolver-cu12==11.4.5.107
Requires-Dist: nvidia-cusparse-cu12==12.1.0.106
Requires-Dist: nvidia-nccl-cu12==2.18.1
Requires-Dist: nvidia-nvjitlink-cu12==12.3.52
Requires-Dist: nvidia-nvtx-cu12==12.1.105
Requires-Dist: overrides==7.4.0
Requires-Dist: packaging==23.2
Requires-Dist: pandas==2.1.3
Requires-Dist: pandocfilters==1.5.0
Requires-Dist: parso==0.8.3
Requires-Dist: pathspec==0.11.2
Requires-Dist: pexpect==4.8.0
Requires-Dist: Pillow==10.1.0
Requires-Dist: platformdirs==4.0.0
Requires-Dist: pluggy==1.3.0
Requires-Dist: prometheus-client==0.18.0
Requires-Dist: prompt-toolkit==3.0.40
Requires-Dist: psutil==5.9.6
Requires-Dist: ptyprocess==0.7.0
Requires-Dist: pure-eval==0.2.2
Requires-Dist: pycodestyle==2.11.1
Requires-Dist: pycparser==2.21
Requires-Dist: pyflakes==3.1.0
Requires-Dist: Pygments==2.16.1
Requires-Dist: pynvml==11.5.0
Requires-Dist: pyparsing==3.1.1
Requires-Dist: pytest==7.4.3
Requires-Dist: python-dateutil==2.8.2
Requires-Dist: python-json-logger==2.0.7
Requires-Dist: pytz==2023.3.post1
Requires-Dist: PyYAML==6.0.1
Requires-Dist: pyzmq==25.1.1
Requires-Dist: qtconsole==5.5.1
Requires-Dist: QtPy==2.4.1
Requires-Dist: referencing==0.31.0
Requires-Dist: regex==2023.10.3
Requires-Dist: requests==2.31.0
Requires-Dist: rfc3339-validator==0.1.4
Requires-Dist: rfc3986-validator==0.1.1
Requires-Dist: rpds-py==0.13.0
Requires-Dist: safetensors==0.4.0
Requires-Dist: sconce
Requires-Dist: Send2Trash==1.8.2
Requires-Dist: six==1.16.0
Requires-Dist: sniffio==1.3.0
Requires-Dist: snntorch==0.7.0
Requires-Dist: snowballstemmer==2.2.0
Requires-Dist: soupsieve==2.5
Requires-Dist: Sphinx==7.2.6
Requires-Dist: sphinx-rtd-theme==1.3.0
Requires-Dist: sphinxcontrib-applehelp==1.0.7
Requires-Dist: sphinxcontrib-devhelp==1.0.5
Requires-Dist: sphinxcontrib-htmlhelp==2.0.4
Requires-Dist: sphinxcontrib-jquery==4.1
Requires-Dist: sphinxcontrib-jsmath==1.0.1
Requires-Dist: sphinxcontrib-qthelp==1.0.6
Requires-Dist: sphinxcontrib-serializinghtml==1.1.9
Requires-Dist: stack-data==0.6.3
Requires-Dist: sympy==1.12
Requires-Dist: terminado==0.18.0
Requires-Dist: tinycss2==1.2.1
Requires-Dist: tokenizers==0.14.1
Requires-Dist: tomli==2.0.1
Requires-Dist: torch==2.1.0
Requires-Dist: torchprofile==0.0.4
Requires-Dist: torchvision==0.16.0
Requires-Dist: tornado==6.3.3
Requires-Dist: tqdm==4.66.1
Requires-Dist: traitlets==5.13.0
Requires-Dist: transformers==4.35.0
Requires-Dist: triton==2.1.0
Requires-Dist: types-python-dateutil==2.8.19.14
Requires-Dist: typing-extensions==4.8.0
Requires-Dist: tzdata==2023.3
Requires-Dist: uri-template==1.3.0
Requires-Dist: urllib3==2.0.7
Requires-Dist: wcwidth==0.2.9
Requires-Dist: webcolors==1.13
Requires-Dist: webencodings==0.5.1
Requires-Dist: websocket-client==1.6.4
Requires-Dist: widgetsnbextension==4.0.9
Requires-Dist: onnx
Requires-Dist: onnxruntime
